CHANGELOG.md
LICENSE.txt
glovo_api_python/__init__.py
glovo_api_python/client.py
glovo_api_python/constants/__init__.py
glovo_api_python/constants/error_codes.py
glovo_api_python/constants/stages.py
glovo_api_python/constants/status_codes.py
glovo_api_python/constants/urls.py
glovo_api_python/errors.py
glovo_api_python/resources/__init__.py
glovo_api_python/resources/base.py
glovo_api_python/resources/order.py
glovo_api_python/resources/working_area.py
glovo_api_python/utils.py
glovo_api_python/version.py
glovo_api_python-2.0.1.dist-info/LICENSE.txt
glovo_api_python-2.0.1.dist-info/WHEEL
glovo_api_python-2.0.1.dist-info/METADATA
glovo_api_python-2.0.1.dist-info/RECORD
