Metadata-Version: 2.1
Name: glovo-api-python
Version: 2.0.1
Summary: Glovo API Python SDK
Home-page: https://gitlab.com/softbutterfly/glovo-api-python
Keywords: Softbutterfly,Glovo,Glovo API
Author: SoftButterfly Development Team
Author-email: dev@softbutterfly.io
Requires-Python: >=3.8,<4.0
Classifier: Development Status :: 5 - Production/Stable
Classifier: Intended Audience :: Developers
Classifier: License :: OSI Approved :: BSD License
Classifier: Natural Language :: English
Classifier: Programming Language :: Python :: 3
Classifier: Programming Language :: Python :: 3.5
Classifier: Programming Language :: Python :: 3.6
Classifier: Programming Language :: Python :: 3.7
Classifier: Programming Language :: Python :: 3.8
Classifier: Topic :: Software Development :: Libraries :: Python Modules
Requires-Dist: requests (>=2.22.0,<3.0.0)
Project-URL: Bug Tracker, https://gitlab.com/softbutterfly/glovo-api-python/-/issues
Project-URL: Documentation, https://gitlab.com/softbutterfly/glovo-api-python/-/wikis/home
Project-URL: Download, https://gitlab.com/softbutterfly/glovo-api-python/-/archive/2.0.1/glovo-api-python-2.0.1.tar.gz
Project-URL: Repository, https://gitlab.com/softbutterfly/glovo-api-python
